LICENSE
MANIFEST.in
README.rst
flask_redistore.py
setup.py
test_redistore.py
Flask_Redistore.egg-info/PKG-INFO
Flask_Redistore.egg-info/SOURCES.txt
Flask_Redistore.egg-info/dependency_links.txt
Flask_Redistore.egg-info/not-zip-safe
Flask_Redistore.egg-info/requires.txt
Flask_Redistore.egg-info/top_level.txt