Metadata-Version: 1.1
Name: Flask-Redistore
Version: 1.0.1
Summary: Adds Redis support to your Flask applications
Home-page: UNKNOWN
Author: Donald Stufft
Author-email: donald.stufft@gmail.com
License: BSD
Platform: any
Classifier: Environment :: Web Environment
Classifier: Intended Audience :: Developers
Classifier: License :: OSI Approved :: BSD License
Classifier: Operating System :: OS Independent
Classifier: Programming Language :: Python
Classifier: Topic :: Internet :: WWW/HTTP :: Dynamic Content
Classifier: Topic :: Software Development :: Libraries :: Python Modules
